lotconfig/__init__.py
lotconfig-1.3.dist-info/DESCRIPTION.rst
lotconfig-1.3.dist-info/METADATA
lotconfig-1.3.dist-info/RECORD
lotconfig-1.3.dist-info/WHEEL
lotconfig-1.3.dist-info/metadata.json
lotconfig-1.3.dist-info/top_level.txt
