Metadata-Version: 2.0
Name: lotconfig
Version: 1.3
Summary: # Lord of the Config
Requires-Dist: dpath
Requires-Dist: pyyaml
